{"cameraMode":{"drawMode":0,"name":"Shaded","section":"Shading Mode"},"sceneLighting":false,"audioPlay":false,"sceneViewState":{"m_AlwaysRefresh":false,"showFog":true,"showSkybox":false,"showFlares":true,"showImageEffects":true,"showParticleSystems":true,"showVisualEffectGraphs":true,"m_FxEnabled":false},"in2DMode":false,"pivot":{"x":-3.9335358142852785,"y":1.490884780883789,"z":4.512479305267334},"rotation":{"x":-0.07658326625823975,"y":-0.6801719069480896,"z":0.07193400710821152,"w":-0.7255273461341858},"size":1.952049732208252,"orthographic":false}